odoo/addons/res_company_search_view/README.rst
odoo/addons/res_company_search_view/__init__.py
odoo/addons/res_company_search_view/__manifest__.py
odoo/addons/res_company_search_view/i18n/es.po
odoo/addons/res_company_search_view/i18n/fr.po
odoo/addons/res_company_search_view/i18n/it.po
odoo/addons/res_company_search_view/i18n/res_company_search_view.pot
odoo/addons/res_company_search_view/readme/CONTRIBUTORS.md
odoo/addons/res_company_search_view/readme/DESCRIPTION.md
odoo/addons/res_company_search_view/static/description/icon.png
odoo/addons/res_company_search_view/static/description/index.html
odoo/addons/res_company_search_view/views/view_res_company.xml
odoo_addon_res_company_search_view-18.0.1.0.0.2.dist-info/METADATA
odoo_addon_res_company_search_view-18.0.1.0.0.2.dist-info/WHEEL
odoo_addon_res_company_search_view-18.0.1.0.0.2.dist-info/top_level.txt
odoo_addon_res_company_search_view-18.0.1.0.0.2.dist-info/RECORD
